{
  "2016-04-quad-desert": [
    {
      "url": "https://mb-sls-engine-shared.s3.amazonaws.com/sample-imagesets/2016-04-quad-desert/2016-04-08 12.14.42-2.jpg",
      "width": 1600,
      "height": 900,
      "orientation": 0,
      "taken_at": "2016-04-08 12:14:42",
      "camera": "SAMSUNG-SM-G928A",
      "camera_make": "samsung",
      "filename": "sample-imagesets/2016-04-quad-desert/2016-04-08 12.14.42-2.jpg",
      "handle": "2016-04-08 12.14.42-2.jpg"
    },
    {
      "url": "https://mb-sls-engine-shared.s3.amazonaws.com/sample-imagesets/2016-04-quad-desert/2016-12-21 16.11.50.jpg",
      "width": 900,
      "height": 1600,
      "orientation": 0,
      "taken_at": "2016-12-21 16:11:50",
      "camera": "SAMSUNG-SM-G928A",
      "camera_make": "samsung",
      "filename": "sample-imagesets/2016-04-quad-desert/2016-12-21 16.11.50.jpg",
      "handle": "2016-12-21 16.11.50.jpg"
    },
    {
      "url": "https://mb-sls-engine-shared.s3.amazonaws.com/sample-imagesets/2016-04-quad-desert/2016-04-08 11.38.07.jpg",
      "width": 1600,
      "height": 900,
      "orientation": 0,
      "taken_at": "2016-04-08 11:38:07",
      "camera": "SAMSUNG-SM-G928A",
      "camera_make": "samsung",
      "filename": "sample-imagesets/2016-04-quad-desert/2016-04-08 11.38.07.jpg",
      "handle": "2016-04-08 11.38.07.jpg"
    },
    {
      "url": "https://mb-sls-engine-shared.s3.amazonaws.com/sample-imagesets/2016-04-quad-desert/2016-12-21 16.10.39.jpg",
      "width": 1600,
      "height": 1580,
      "orientation": 0,
      "taken_at": "2016-12-21 16:10:39",
      "camera": "SAMSUNG-SM-G928A",
      "camera_make": "samsung",
      "filename": "sample-imagesets/2016-04-quad-desert/2016-12-21 16.10.39.jpg",
      "handle": "2016-12-21 16.10.39.jpg"
    },
    {
      "url": "https://mb-sls-engine-shared.s3.amazonaws.com/sample-imagesets/2016-04-quad-desert/2016-12-21 14.37.02.jpg",
      "width": 900,
      "height": 1600,
      "orientation": 0,
      "taken_at": "2016-12-21 14:37:02",
      "camera": "SAMSUNG-SM-G928A",
      "camera_make": "samsung",
      "filename": "sample-imagesets/2016-04-quad-desert/2016-12-21 14.37.02.jpg",
      "handle": "2016-12-21 14.37.02.jpg"
    },
    {
      "url": "https://mb-sls-engine-shared.s3.amazonaws.com/sample-imagesets/2016-04-quad-desert/2016-04-08 12.05.39.jpg",
      "width": 1600,
      "height": 900,
      "orientation": 0,
      "taken_at": "2016-04-08 12:05:39",
      "camera": "SAMSUNG-SM-G928A",
      "camera_make": "samsung",
      "filename": "sample-imagesets/2016-04-quad-desert/2016-04-08 12.05.39.jpg",
      "handle": "2016-04-08 12.05.39.jpg"
    },
    {
      "url": "https://mb-sls-engine-shared.s3.amazonaws.com/sample-imagesets/2016-04-quad-desert/2016-12-21 16.13.42.jpg",
      "width": 1600,
      "height": 900,
      "orientation": 0,
      "taken_at": "2016-12-21 16:13:42",
      "camera": "SAMSUNG-SM-G928A",
      "camera_make": "samsung",
      "filename": "sample-imagesets/2016-04-quad-desert/2016-12-21 16.13.42.jpg",
      "handle": "2016-12-21 16.13.42.jpg"
    },
    {
      "url": "https://mb-sls-engine-shared.s3.amazonaws.com/sample-imagesets/2016-04-quad-desert/2016-08-24_10.39.57.jpg",
      "width": 1600,
      "height": 1200,
      "orientation": 0,
      "taken_at": "2016-08-24 10:39:57",
      "camera": "SAMSUNG-SM-G928A",
      "camera_make": "samsung",
      "filename": "sample-imagesets/2016-04-quad-desert/2016-08-24_10.39.57.jpg",
      "handle": "2016-08-24_10.39.57.jpg"
    },
    {
      "url": "https://mb-sls-engine-shared.s3.amazonaws.com/sample-imagesets/2016-04-quad-desert/2016-04-08 11.45.00.jpg",
      "width": 1600,
      "height": 1219,
      "orientation": 0,
      "taken_at": "2016-04-08 11:45:00",
      "camera": "SAMSUNG-SM-G928A",
      "camera_make": "samsung",
      "filename": "sample-imagesets/2016-04-quad-desert/2016-04-08 11.45.00.jpg",
      "handle": "2016-04-08 11.45.00.jpg"
    },
    {
      "url": "https://mb-sls-engine-shared.s3.amazonaws.com/sample-imagesets/2016-04-quad-desert/2016-08-24_10.39.53.jpg",
      "width": 1600,
      "height": 1200,
      "orientation": 0,
      "taken_at": "2016-08-24 10:39:53",
      "camera": "SAMSUNG-SM-G928A",
      "camera_make": "samsung",
      "filename": "sample-imagesets/2016-04-quad-desert/2016-08-24_10.39.53.jpg",
      "handle": "2016-08-24_10.39.53.jpg"
    },
    {
      "url": "https://mb-sls-engine-shared.s3.amazonaws.com/sample-imagesets/2016-04-quad-desert/2016-04-08 11.26.29.jpg",
      "width": 1600,
      "height": 900,
      "orientation": 0,
      "taken_at": "2016-04-08 11:26:29",
      "camera": "SAMSUNG-SM-G928A",
      "camera_make": "samsung",
      "filename": "sample-imagesets/2016-04-quad-desert/2016-04-08 11.26.29.jpg",
      "handle": "2016-04-08 11.26.29.jpg"
    },
    {
      "url": "https://mb-sls-engine-shared.s3.amazonaws.com/sample-imagesets/2016-04-quad-desert/2016-04-08 10.56.22.jpg",
      "width": 1600,
      "height": 900,
      "orientation": 0,
      "taken_at": "2016-04-08 10:56:22",
      "camera": "SAMSUNG-SM-G928A",
      "camera_make": "samsung",
      "filename": "sample-imagesets/2016-04-quad-desert/2016-04-08 10.56.22.jpg",
      "handle": "2016-04-08 10.56.22.jpg"
    },
    {
      "url": "https://mb-sls-engine-shared.s3.amazonaws.com/sample-imagesets/2016-04-quad-desert/2016-12-21 13.21.38.jpg",
      "width": 1600,
      "height": 553,
      "orientation": 0,
      "taken_at": "2016-12-21 13:21:38",
      "camera": "SAMSUNG-SM-G928A",
      "camera_make": "samsung",
      "filename": "sample-imagesets/2016-04-quad-desert/2016-12-21 13.21.38.jpg",
      "handle": "2016-12-21 13.21.38.jpg"
    },
    {
      "url": "https://mb-sls-engine-shared.s3.amazonaws.com/sample-imagesets/2016-04-quad-desert/2016-04-08 12.29.33-2.jpg",
      "width": 1600,
      "height": 900,
      "orientation": 0,
      "taken_at": "2016-04-08 12:29:33",
      "camera": "SAMSUNG-SM-G928A",
      "camera_make": "samsung",
      "filename": "sample-imagesets/2016-04-quad-desert/2016-04-08 12.29.33-2.jpg",
      "handle": "2016-04-08 12.29.33-2.jpg"
    },
    {
      "url": "https://mb-sls-engine-shared.s3.amazonaws.com/sample-imagesets/2016-04-quad-desert/2016-08-24_12.37.03.jpg",
      "width": 1600,
      "height": 1200,
      "orientation": 0,
      "taken_at": "2016-08-24 12:37:03",
      "camera": "SAMSUNG-SM-G928A",
      "camera_make": "samsung",
      "filename": "sample-imagesets/2016-04-quad-desert/2016-08-24_12.37.03.jpg",
      "handle": "2016-08-24_12.37.03.jpg"
    },
    {
      "url": "https://mb-sls-engine-shared.s3.amazonaws.com/sample-imagesets/2016-04-quad-desert/2016-04-08 12.23.13.jpg",
      "width": 900,
      "height": 1600,
      "orientation": 0,
      "taken_at": "2016-04-08 12:23:13",
      "camera": "SAMSUNG-SM-G928A",
      "camera_make": "samsung",
      "filename": "sample-imagesets/2016-04-quad-desert/2016-04-08 12.23.13.jpg",
      "handle": "2016-04-08 12.23.13.jpg"
    },
    {
      "url": "https://mb-sls-engine-shared.s3.amazonaws.com/sample-imagesets/2016-04-quad-desert/2016-12-21 16.11.55.jpg",
      "width": 900,
      "height": 1600,
      "orientation": 0,
      "taken_at": "2016-12-21 16:11:55",
      "camera": "SAMSUNG-SM-G928A",
      "camera_make": "samsung",
      "filename": "sample-imagesets/2016-04-quad-desert/2016-12-21 16.11.55.jpg",
      "handle": "2016-12-21 16.11.55.jpg"
    },
    {
      "url": "https://mb-sls-engine-shared.s3.amazonaws.com/sample-imagesets/2016-04-quad-desert/2016-04-08 10.58.31.jpg",
      "width": 1600,
      "height": 874,
      "orientation": 0,
      "taken_at": "2016-04-08 10:58:31",
      "camera": "SAMSUNG-SM-G928A",
      "camera_make": "samsung",
      "filename": "sample-imagesets/2016-04-quad-desert/2016-04-08 10.58.31.jpg",
      "handle": "2016-04-08 10.58.31.jpg"
    },
    {
      "url": "https://mb-sls-engine-shared.s3.amazonaws.com/sample-imagesets/2016-04-quad-desert/2016-12-21 16.48.40.jpg",
      "width": 1600,
      "height": 1200,
      "orientation": 0,
      "taken_at": "2016-12-21 16:48:40",
      "camera": "SAMSUNG-SM-G928A",
      "camera_make": "samsung",
      "filename": "sample-imagesets/2016-04-quad-desert/2016-12-21 16.48.40.jpg",
      "handle": "2016-12-21 16.48.40.jpg"
    },
    {
      "url": "https://mb-sls-engine-shared.s3.amazonaws.com/sample-imagesets/2016-04-quad-desert/2016-04-08 11.37.08.jpg",
      "width": 1600,
      "height": 900,
      "orientation": 0,
      "taken_at": "2016-04-08 11:37:08",
      "camera": "SAMSUNG-SM-G928A",
      "camera_make": "samsung",
      "filename": "sample-imagesets/2016-04-quad-desert/2016-04-08 11.37.08.jpg",
      "handle": "2016-04-08 11.37.08.jpg"
    },
    {
      "url": "https://mb-sls-engine-shared.s3.amazonaws.com/sample-imagesets/2016-04-quad-desert/2016-04-08 10.56.46.jpg",
      "width": 1600,
      "height": 1275,
      "orientation": 0,
      "taken_at": "2016-04-08 10:56:46",
      "camera": "SAMSUNG-SM-G928A",
      "camera_make": "samsung",
      "filename": "sample-imagesets/2016-04-quad-desert/2016-04-08 10.56.46.jpg",
      "handle": "2016-04-08 10.56.46.jpg"
    },
    {
      "url": "https://mb-sls-engine-shared.s3.amazonaws.com/sample-imagesets/2016-04-quad-desert/2016-08-24_11.11.41.jpg",
      "width": 1200,
      "height": 1600,
      "orientation": 0,
      "taken_at": "2016-08-24 11:11:41",
      "camera": "SAMSUNG-SM-G928A",
      "camera_make": "samsung",
      "filename": "sample-imagesets/2016-04-quad-desert/2016-08-24_11.11.41.jpg",
      "handle": "2016-08-24_11.11.41.jpg"
    },
    {
      "url": "https://mb-sls-engine-shared.s3.amazonaws.com/sample-imagesets/2016-04-quad-desert/2016-12-21 14.02.25.jpg",
      "width": 900,
      "height": 1600,
      "orientation": 0,
      "taken_at": "2016-12-21 14:02:25",
      "camera": "SAMSUNG-SM-G928A",
      "camera_make": "samsung",
      "filename": "sample-imagesets/2016-04-quad-desert/2016-12-21 14.02.25.jpg",
      "handle": "2016-12-21 14.02.25.jpg"
    },
    {
      "url": "https://mb-sls-engine-shared.s3.amazonaws.com/sample-imagesets/2016-04-quad-desert/2016-04-08 11.27.26.jpg",
      "width": 1600,
      "height": 900,
      "orientation": 0,
      "taken_at": "2016-04-08 11:27:26",
      "camera": "SAMSUNG-SM-G928A",
      "camera_make": "samsung",
      "filename": "sample-imagesets/2016-04-quad-desert/2016-04-08 11.27.26.jpg",
      "handle": "2016-04-08 11.27.26.jpg"
    },
    {
      "url": "https://mb-sls-engine-shared.s3.amazonaws.com/sample-imagesets/2016-04-quad-desert/2016-12-21 16.11.24.jpg",
      "width": 1600,
      "height": 900,
      "orientation": 0,
      "taken_at": "2016-12-21 16:11:24",
      "camera": "SAMSUNG-SM-G928A",
      "camera_make": "samsung",
      "filename": "sample-imagesets/2016-04-quad-desert/2016-12-21 16.11.24.jpg",
      "handle": "2016-12-21 16.11.24.jpg"
    },
    {
      "url": "https://mb-sls-engine-shared.s3.amazonaws.com/sample-imagesets/2016-04-quad-desert/2016-08-24_11.59.06.jpg",
      "width": 1600,
      "height": 407,
      "orientation": 0,
      "taken_at": "2016-08-24 11:59:06",
      "camera": "SAMSUNG-SM-G928A",
      "camera_make": "samsung",
      "filename": "sample-imagesets/2016-04-quad-desert/2016-08-24_11.59.06.jpg",
      "handle": "2016-08-24_11.59.06.jpg"
    },
    {
      "url": "https://mb-sls-engine-shared.s3.amazonaws.com/sample-imagesets/2016-04-quad-desert/2016-08-24_09.56.23.jpg",
      "width": 1600,
      "height": 1200,
      "orientation": 0,
      "taken_at": "2016-08-24 09:56:23",
      "camera": "SAMSUNG-SM-G928A",
      "camera_make": "samsung",
      "filename": "sample-imagesets/2016-04-quad-desert/2016-08-24_09.56.23.jpg",
      "handle": "2016-08-24_09.56.23.jpg"
    },
    {
      "url": "https://mb-sls-engine-shared.s3.amazonaws.com/sample-imagesets/2016-04-quad-desert/2016-12-21 16.10.59.jpg",
      "width": 900,
      "height": 1600,
      "orientation": 0,
      "taken_at": "2016-12-21 16:10:59",
      "camera": "SAMSUNG-SM-G928A",
      "camera_make": "samsung",
      "filename": "sample-imagesets/2016-04-quad-desert/2016-12-21 16.10.59.jpg",
      "handle": "2016-12-21 16.10.59.jpg"
    },
    {
      "url": "https://mb-sls-engine-shared.s3.amazonaws.com/sample-imagesets/2016-04-quad-desert/2016-12-21 14.02.21.jpg",
      "width": 1600,
      "height": 900,
      "orientation": 0,
      "taken_at": "2016-12-21 14:02:21",
      "camera": "SAMSUNG-SM-G928A",
      "camera_make": "samsung",
      "filename": "sample-imagesets/2016-04-quad-desert/2016-12-21 14.02.21.jpg",
      "handle": "2016-12-21 14.02.21.jpg"
    },
    {
      "url": "https://mb-sls-engine-shared.s3.amazonaws.com/sample-imagesets/2016-04-quad-desert/2016-04-08 10.59.13.jpg",
      "width": 900,
      "height": 1600,
      "orientation": 0,
      "taken_at": "2016-04-08 10:59:13",
      "camera": "SAMSUNG-SM-G928A",
      "camera_make": "samsung",
      "filename": "sample-imagesets/2016-04-quad-desert/2016-04-08 10.59.13.jpg",
      "handle": "2016-04-08 10.59.13.jpg"
    },
    {
      "url": "https://mb-sls-engine-shared.s3.amazonaws.com/sample-imagesets/2016-04-quad-desert/2016-04-08 11.38.10-1.jpg",
      "width": 1600,
      "height": 900,
      "orientation": 0,
      "taken_at": "2016-04-08 11:38:10",
      "camera": "SAMSUNG-SM-G928A",
      "camera_make": "samsung",
      "filename": "sample-imagesets/2016-04-quad-desert/2016-04-08 11.38.10-1.jpg",
      "handle": "2016-04-08 11.38.10-1.jpg"
    },
    {
      "url": "https://mb-sls-engine-shared.s3.amazonaws.com/sample-imagesets/2016-04-quad-desert/2016-08-24_12.37.49.jpg",
      "width": 1600,
      "height": 1200,
      "orientation": 0,
      "taken_at": "2016-08-24 12:37:49",
      "camera": "SAMSUNG-SM-G928A",
      "camera_make": "samsung",
      "filename": "sample-imagesets/2016-04-quad-desert/2016-08-24_12.37.49.jpg",
      "handle": "2016-08-24_12.37.49.jpg"
    },
    {
      "url": "https://mb-sls-engine-shared.s3.amazonaws.com/sample-imagesets/2016-04-quad-desert/2016-08-24_11.57.35.jpg",
      "width": 1600,
      "height": 605,
      "orientation": 0,
      "taken_at": "2016-08-24 11:57:35",
      "camera": "SAMSUNG-SM-G928A",
      "camera_make": "samsung",
      "filename": "sample-imagesets/2016-04-quad-desert/2016-08-24_11.57.35.jpg",
      "handle": "2016-08-24_11.57.35.jpg"
    },
    {
      "url": "https://mb-sls-engine-shared.s3.amazonaws.com/sample-imagesets/2016-04-quad-desert/2016-12-21 16.10.46.jpg",
      "width": 900,
      "height": 1600,
      "orientation": 0,
      "taken_at": "2016-12-21 16:10:46",
      "camera": "SAMSUNG-SM-G928A",
      "camera_make": "samsung",
      "filename": "sample-imagesets/2016-04-quad-desert/2016-12-21 16.10.46.jpg",
      "handle": "2016-12-21 16.10.46.jpg"
    },
    {
      "url": "https://mb-sls-engine-shared.s3.amazonaws.com/sample-imagesets/2016-04-quad-desert/2016-08-24_09.56.14.jpg",
      "width": 1600,
      "height": 1200,
      "orientation": 0,
      "taken_at": "2016-08-24 09:56:14",
      "camera": "SAMSUNG-SM-G928A",
      "camera_make": "samsung",
      "filename": "sample-imagesets/2016-04-quad-desert/2016-08-24_09.56.14.jpg",
      "handle": "2016-08-24_09.56.14.jpg"
    },
    {
      "url": "https://mb-sls-engine-shared.s3.amazonaws.com/sample-imagesets/2016-04-quad-desert/2016-04-08 11.37.14.jpg",
      "width": 1600,
      "height": 900,
      "orientation": 0,
      "taken_at": "2016-04-08 11:37:14",
      "camera": "SAMSUNG-SM-G928A",
      "camera_make": "samsung",
      "filename": "sample-imagesets/2016-04-quad-desert/2016-04-08 11.37.14.jpg",
      "handle": "2016-04-08 11.37.14.jpg"
    },
    {
      "url": "https://mb-sls-engine-shared.s3.amazonaws.com/sample-imagesets/2016-04-quad-desert/2016-12-21 14.46.56.jpg",
      "width": 1600,
      "height": 900,
      "orientation": 0,
      "taken_at": "2016-12-21 14:46:56",
      "camera": "SAMSUNG-SM-G928A",
      "camera_make": "samsung",
      "filename": "sample-imagesets/2016-04-quad-desert/2016-12-21 14.46.56.jpg",
      "handle": "2016-12-21 14.46.56.jpg"
    },
    {
      "url": "https://mb-sls-engine-shared.s3.amazonaws.com/sample-imagesets/2016-04-quad-desert/2016-12-21 14.46.42.jpg",
      "width": 944,
      "height": 1600,
      "orientation": 0,
      "taken_at": "2016-12-21 14:46:42",
      "camera": "SAMSUNG-SM-G928A",
      "camera_make": "samsung",
      "filename": "sample-imagesets/2016-04-quad-desert/2016-12-21 14.46.42.jpg",
      "handle": "2016-12-21 14.46.42.jpg"
    },
    {
      "url": "https://mb-sls-engine-shared.s3.amazonaws.com/sample-imagesets/2016-04-quad-desert/2016-12-21 16.11.39.jpg",
      "width": 900,
      "height": 1600,
      "orientation": 0,
      "taken_at": "2016-12-21 16:11:39",
      "camera": "SAMSUNG-SM-G928A",
      "camera_make": "samsung",
      "filename": "sample-imagesets/2016-04-quad-desert/2016-12-21 16.11.39.jpg",
      "handle": "2016-12-21 16.11.39.jpg"
    },
    {
      "url": "https://mb-sls-engine-shared.s3.amazonaws.com/sample-imagesets/2016-04-quad-desert/2016-12-21 16.10.50.jpg",
      "width": 900,
      "height": 1600,
      "orientation": 0,
      "taken_at": "2016-12-21 16:10:50",
      "camera": "SAMSUNG-SM-G928A",
      "camera_make": "samsung",
      "filename": "sample-imagesets/2016-04-quad-desert/2016-12-21 16.10.50.jpg",
      "handle": "2016-12-21 16.10.50.jpg"
    },
    {
      "url": "https://mb-sls-engine-shared.s3.amazonaws.com/sample-imagesets/2016-04-quad-desert/2016-04-08 11.38.43.jpg",
      "width": 1600,
      "height": 900,
      "orientation": 0,
      "taken_at": "2016-04-08 11:38:43",
      "camera": "SAMSUNG-SM-G928A",
      "camera_make": "samsung",
      "filename": "sample-imagesets/2016-04-quad-desert/2016-04-08 11.38.43.jpg",
      "handle": "2016-04-08 11.38.43.jpg"
    },
    {
      "url": "https://mb-sls-engine-shared.s3.amazonaws.com/sample-imagesets/2016-04-quad-desert/2016-12-21 16.11.15.jpg",
      "width": 900,
      "height": 1600,
      "orientation": 0,
      "taken_at": "2016-12-21 16:11:15",
      "camera": "SAMSUNG-SM-G928A",
      "camera_make": "samsung",
      "filename": "sample-imagesets/2016-04-quad-desert/2016-12-21 16.11.15.jpg",
      "handle": "2016-12-21 16.11.15.jpg"
    },
    {
      "url": "https://mb-sls-engine-shared.s3.amazonaws.com/sample-imagesets/2016-04-quad-desert/2016-04-08 11.27.03.jpg",
      "width": 766,
      "height": 1337,
      "orientation": 0,
      "taken_at": "2016-04-08 11:27:03",
      "camera": "SAMSUNG-SM-G928A",
      "camera_make": "samsung",
      "filename": "sample-imagesets/2016-04-quad-desert/2016-04-08 11.27.03.jpg",
      "handle": "2016-04-08 11.27.03.jpg"
    },
    {
      "url": "https://mb-sls-engine-shared.s3.amazonaws.com/sample-imagesets/2016-04-quad-desert/2016-12-21 16.12.52.jpg",
      "width": 1600,
      "height": 900,
      "orientation": 0,
      "taken_at": "2016-12-21 16:12:52",
      "camera": "SAMSUNG-SM-G928A",
      "camera_make": "samsung",
      "filename": "sample-imagesets/2016-04-quad-desert/2016-12-21 16.12.52.jpg",
      "handle": "2016-12-21 16.12.52.jpg"
    },
    {
      "url": "https://mb-sls-engine-shared.s3.amazonaws.com/sample-imagesets/2016-04-quad-desert/2016-04-08 11.27.01.jpg",
      "width": 1600,
      "height": 584,
      "orientation": 0,
      "taken_at": "2016-04-08 11:27:01",
      "camera": "SAMSUNG-SM-G928A",
      "camera_make": "samsung",
      "filename": "sample-imagesets/2016-04-quad-desert/2016-04-08 11.27.01.jpg",
      "handle": "2016-04-08 11.27.01.jpg"
    },
    {
      "url": "https://mb-sls-engine-shared.s3.amazonaws.com/sample-imagesets/2016-04-quad-desert/2016-04-08 12.29.56.jpg",
      "width": 900,
      "height": 1600,
      "orientation": 0,
      "taken_at": "2016-04-08 12:29:56",
      "camera": "SAMSUNG-SM-G928A",
      "camera_make": "samsung",
      "filename": "sample-imagesets/2016-04-quad-desert/2016-04-08 12.29.56.jpg",
      "handle": "2016-04-08 12.29.56.jpg"
    },
    {
      "url": "https://mb-sls-engine-shared.s3.amazonaws.com/sample-imagesets/2016-04-quad-desert/2016-08-24_11.58.13.jpg",
      "width": 1200,
      "height": 1600,
      "orientation": 0,
      "taken_at": "2016-08-24 11:58:13",
      "camera": "SAMSUNG-SM-G928A",
      "camera_make": "samsung",
      "filename": "sample-imagesets/2016-04-quad-desert/2016-08-24_11.58.13.jpg",
      "handle": "2016-08-24_11.58.13.jpg"
    },
    {
      "url": "https://mb-sls-engine-shared.s3.amazonaws.com/sample-imagesets/2016-04-quad-desert/2016-04-08 12.23.22.jpg",
      "width": 900,
      "height": 1600,
      "orientation": 0,
      "taken_at": "2016-04-08 12:23:22",
      "camera": "SAMSUNG-SM-G928A",
      "camera_make": "samsung",
      "filename": "sample-imagesets/2016-04-quad-desert/2016-04-08 12.23.22.jpg",
      "handle": "2016-04-08 12.23.22.jpg"
    },
    {
      "url": "https://mb-sls-engine-shared.s3.amazonaws.com/sample-imagesets/2016-04-quad-desert/2016-12-21 13.21.35.jpg",
      "width": 1600,
      "height": 500,
      "orientation": 0,
      "taken_at": "2016-12-21 13:21:35",
      "camera": "SAMSUNG-SM-G928A",
      "camera_make": "samsung",
      "filename": "sample-imagesets/2016-04-quad-desert/2016-12-21 13.21.35.jpg",
      "handle": "2016-12-21 13.21.35.jpg"
    },
    {
      "url": "https://mb-sls-engine-shared.s3.amazonaws.com/sample-imagesets/2016-04-quad-desert/2016-04-08 12.25.55.jpg",
      "width": 1600,
      "height": 900,
      "orientation": 0,
      "taken_at": "2016-04-08 12:25:55",
      "camera": "SAMSUNG-SM-G928A",
      "camera_make": "samsung",
      "filename": "sample-imagesets/2016-04-quad-desert/2016-04-08 12.25.55.jpg",
      "handle": "2016-04-08 12.25.55.jpg"
    },
    {
      "url": "https://mb-sls-engine-shared.s3.amazonaws.com/sample-imagesets/2016-04-quad-desert/2016-08-24_10.40.13.jpg",
      "width": 1200,
      "height": 1600,
      "orientation": 0,
      "taken_at": "2016-08-24 10:40:13",
      "camera": "SAMSUNG-SM-G928A",
      "camera_make": "samsung",
      "filename": "sample-imagesets/2016-04-quad-desert/2016-08-24_10.40.13.jpg",
      "handle": "2016-08-24_10.40.13.jpg"
    },
    {
      "url": "https://mb-sls-engine-shared.s3.amazonaws.com/sample-imagesets/2016-04-quad-desert/2016-04-08 23.27.14.jpg",
      "width": 1489,
      "height": 1600,
      "orientation": 0,
      "taken_at": "2016-04-08 15:27:14",
      "camera": "SAMSUNG-SM-G928A",
      "camera_make": "samsung",
      "filename": "sample-imagesets/2016-04-quad-desert/2016-04-08 23.27.14.jpg",
      "handle": "2016-04-08 23.27.14.jpg"
    },
    {
      "url": "https://mb-sls-engine-shared.s3.amazonaws.com/sample-imagesets/2016-04-quad-desert/2016-04-08 12.05.25.jpg",
      "width": 1600,
      "height": 900,
      "orientation": 0,
      "taken_at": "2016-04-08 12:05:25",
      "camera": "SAMSUNG-SM-G928A",
      "camera_make": "samsung",
      "filename": "sample-imagesets/2016-04-quad-desert/2016-04-08 12.05.25.jpg",
      "handle": "2016-04-08 12.05.25.jpg"
    },
    {
      "url": "https://mb-sls-engine-shared.s3.amazonaws.com/sample-imagesets/2016-04-quad-desert/2016-04-08 12.05.21.jpg",
      "width": 1600,
      "height": 1200,
      "orientation": 0,
      "taken_at": "2016-04-08 12:05:21",
      "camera": "SAMSUNG-SM-G928A",
      "camera_make": "samsung",
      "filename": "sample-imagesets/2016-04-quad-desert/2016-04-08 12.05.21.jpg",
      "handle": "2016-04-08 12.05.21.jpg"
    },
    {
      "url": "https://mb-sls-engine-shared.s3.amazonaws.com/sample-imagesets/2016-04-quad-desert/2016-04-08 11.26.34.jpg",
      "width": 1600,
      "height": 900,
      "orientation": 0,
      "taken_at": "2016-04-08 11:26:34",
      "camera": "SAMSUNG-SM-G928A",
      "camera_make": "samsung",
      "filename": "sample-imagesets/2016-04-quad-desert/2016-04-08 11.26.34.jpg",
      "handle": "2016-04-08 11.26.34.jpg"
    },
    {
      "url": "https://mb-sls-engine-shared.s3.amazonaws.com/sample-imagesets/2016-04-quad-desert/2016-12-21 13.21.19.jpg",
      "width": 1600,
      "height": 900,
      "orientation": 0,
      "taken_at": "2016-12-21 13:21:19",
      "camera": "SAMSUNG-SM-G928A",
      "camera_make": "samsung",
      "filename": "sample-imagesets/2016-04-quad-desert/2016-12-21 13.21.19.jpg",
      "handle": "2016-12-21 13.21.19.jpg"
    },
    {
      "url": "https://mb-sls-engine-shared.s3.amazonaws.com/sample-imagesets/2016-04-quad-desert/2016-04-08 10.57.54.jpg",
      "width": 1600,
      "height": 921,
      "orientation": 0,
      "taken_at": "2016-04-08 10:57:54",
      "camera": "SAMSUNG-SM-G928A",
      "camera_make": "samsung",
      "filename": "sample-imagesets/2016-04-quad-desert/2016-04-08 10.57.54.jpg",
      "handle": "2016-04-08 10.57.54.jpg"
    },
    {
      "url": "https://mb-sls-engine-shared.s3.amazonaws.com/sample-imagesets/2016-04-quad-desert/2016-04-08 12.05.37.jpg",
      "width": 1600,
      "height": 900,
      "orientation": 0,
      "taken_at": "2016-04-08 12:05:37",
      "camera": "SAMSUNG-SM-G928A",
      "camera_make": "samsung",
      "filename": "sample-imagesets/2016-04-quad-desert/2016-04-08 12.05.37.jpg",
      "handle": "2016-04-08 12.05.37.jpg"
    },
    {
      "url": "https://mb-sls-engine-shared.s3.amazonaws.com/sample-imagesets/2016-04-quad-desert/2016-04-08 11.34.37.jpg",
      "width": 900,
      "height": 1600,
      "orientation": 0,
      "taken_at": "2016-04-08 11:34:37",
      "camera": "SAMSUNG-SM-G928A",
      "camera_make": "samsung",
      "filename": "sample-imagesets/2016-04-quad-desert/2016-04-08 11.34.37.jpg",
      "handle": "2016-04-08 11.34.37.jpg"
    }
  ]
}
